[
  {
    "hash": "01112231415161718191101111122",
    "decodedHash": [
      {
        "0": 1
      },
      {
        "1": 1
      },
      {
        "2": 2
      },
      {
        "3": 1
      },
      {
        "4": 1
      },
      {
        "5": 1
      },
      {
        "6": 1
      },
      {
        "7": 1
      },
      {
        "8": 1
      },
      {
        "9": 1
      },
      {
        "10": 1
      },
      {
        "11": 1
      },
      {
        "12": 2
      }
    ],
    "edition": 1,
    "date": 1644552322752,
    "attributes": [
      {
        "id": 1,
        "layer": "nameplate",
        "name": "nameplate",
        "rarity": "original"
      },
      {
        "id": 1,
        "layer": "face",
        "name": "face",
        "rarity": "original"
      },
      {
        "id": 2,
        "layer": "hair",
        "name": "hair 3",
        "rarity": "original"
      },
      {
        "id": 1,
        "layer": "moustache",
        "name": "moustache",
        "rarity": "original"
      },
      {
        "id": 1,
        "layer": "eyebrows",
        "name": "eyebrows",
        "rarity": "original"
      },
      {
        "id": 1,
        "layer": "goatee",
        "name": "goatee",
        "rarity": "original"
      },
      {
        "id": 1,
        "layer": "nose",
        "name": "nose",
        "rarity": "original"
      },
      {
        "id": 1,
        "layer": "eyes",
        "name": "eyes",
        "rarity": "original"
      },
      {
        "id": 1,
        "layer": "teeth",
        "name": "teeth",
        "rarity": "original"
      },
      {
        "id": 1,
        "layer": "pupils",
        "name": "pupils",
        "rarity": "original"
      },
      {
        "id": 1,
        "layer": "lips",
        "name": "lips",
        "rarity": "original"
      },
      {
        "id": 1,
        "layer": "blunt_body",
        "name": "blunt_body",
        "rarity": "original"
      },
      {
        "id": 2,
        "layer": "blunt_smoke",
        "name": "blunt_smokeeddish",
        "rarity": "rare"
      }
    ]
  },
  {
    "hash": "01112331415161718191101111121",
    "decodedHash": [
      {
        "0": 1
      },
      {
        "1": 1
      },
      {
        "2": 3
      },
      {
        "3": 1
      },
      {
        "4": 1
      },
      {
        "5": 1
      },
      {
        "6": 1
      },
      {
        "7": 1
      },
      {
        "8": 1
      },
      {
        "9": 1
      },
      {
        "10": 1
      },
      {
        "11": 1
      },
      {
        "12": 1
      }
    ],
    "edition": 2,
    "date": 1644552323623,
    "attributes": [
      {
        "id": 1,
        "layer": "nameplate",
        "name": "nameplate",
        "rarity": "original"
      },
      {
        "id": 1,
        "layer": "face",
        "name": "face",
        "rarity": "original"
      },
      {
        "id": 3,
        "layer": "hair",
        "name": "hair 4",
        "rarity": "original"
      },
      {
        "id": 1,
        "layer": "moustache",
        "name": "moustache",
        "rarity": "original"
      },
      {
        "id": 1,
        "layer": "eyebrows",
        "name": "eyebrows",
        "rarity": "original"
      },
      {
        "id": 1,
        "layer": "goatee",
        "name": "goatee",
        "rarity": "original"
      },
      {
        "id": 1,
        "layer": "nose",
        "name": "nose",
        "rarity": "original"
      },
      {
        "id": 1,
        "layer": "eyes",
        "name": "eyes",
        "rarity": "original"
      },
      {
        "id": 1,
        "layer": "teeth",
        "name": "teeth",
        "rarity": "original"
      },
      {
        "id": 1,
        "layer": "pupils",
        "name": "pupils",
        "rarity": "original"
      },
      {
        "id": 1,
        "layer": "lips",
        "name": "lips",
        "rarity": "original"
      },
      {
        "id": 1,
        "layer": "blunt_body",
        "name": "blunt_body",
        "rarity": "original"
      },
      {
        "id": 1,
        "layer": "blunt_smoke",
        "name": "blunt_smoke",
        "rarity": "original"
      }
    ]
  },
  {
    "hash": "01112431415161718191101111121",
    "decodedHash": [
      {
        "0": 1
      },
      {
        "1": 1
      },
      {
        "2": 4
      },
      {
        "3": 1
      },
      {
        "4": 1
      },
      {
        "5": 1
      },
      {
        "6": 1
      },
      {
        "7": 1
      },
      {
        "8": 1
      },
      {
        "9": 1
      },
      {
        "10": 1
      },
      {
        "11": 1
      },
      {
        "12": 1
      }
    ],
    "edition": 3,
    "date": 1644552324481,
    "attributes": [
      {
        "id": 1,
        "layer": "nameplate",
        "name": "nameplate",
        "rarity": "original"
      },
      {
        "id": 1,
        "layer": "face",
        "name": "face",
        "rarity": "original"
      },
      {
        "id": 4,
        "layer": "hair",
        "name": "hair 5",
        "rarity": "original"
      },
      {
        "id": 1,
        "layer": "moustache",
        "name": "moustache",
        "rarity": "original"
      },
      {
        "id": 1,
        "layer": "eyebrows",
        "name": "eyebrows",
        "rarity": "original"
      },
      {
        "id": 1,
        "layer": "goatee",
        "name": "goatee",
        "rarity": "original"
      },
      {
        "id": 1,
        "layer": "nose",
        "name": "nose",
        "rarity": "original"
      },
      {
        "id": 1,
        "layer": "eyes",
        "name": "eyes",
        "rarity": "original"
      },
      {
        "id": 1,
        "layer": "teeth",
        "name": "teeth",
        "rarity": "original"
      },
      {
        "id": 1,
        "layer": "pupils",
        "name": "pupils",
        "rarity": "original"
      },
      {
        "id": 1,
        "layer": "lips",
        "name": "lips",
        "rarity": "original"
      },
      {
        "id": 1,
        "layer": "blunt_body",
        "name": "blunt_body",
        "rarity": "original"
      },
      {
        "id": 1,
        "layer": "blunt_smoke",
        "name": "blunt_smoke",
        "rarity": "original"
      }
    ]
  },
  {
    "hash": "01112131415161718191101111121",
    "decodedHash": [
      {
        "0": 1
      },
      {
        "1": 1
      },
      {
        "2": 1
      },
      {
        "3": 1
      },
      {
        "4": 1
      },
      {
        "5": 1
      },
      {
        "6": 1
      },
      {
        "7": 1
      },
      {
        "8": 1
      },
      {
        "9": 1
      },
      {
        "10": 1
      },
      {
        "11": 1
      },
      {
        "12": 1
      }
    ],
    "edition": 4,
    "date": 1644552325336,
    "attributes": [
      {
        "id": 1,
        "layer": "nameplate",
        "name": "nameplate",
        "rarity": "original"
      },
      {
        "id": 1,
        "layer": "face",
        "name": "face",
        "rarity": "original"
      },
      {
        "id": 1,
        "layer": "hair",
        "name": "hair 2",
        "rarity": "original"
      },
      {
        "id": 1,
        "layer": "moustache",
        "name": "moustache",
        "rarity": "original"
      },
      {
        "id": 1,
        "layer": "eyebrows",
        "name": "eyebrows",
        "rarity": "original"
      },
      {
        "id": 1,
        "layer": "goatee",
        "name": "goatee",
        "rarity": "original"
      },
      {
        "id": 1,
        "layer": "nose",
        "name": "nose",
        "rarity": "original"
      },
      {
        "id": 1,
        "layer": "eyes",
        "name": "eyes",
        "rarity": "original"
      },
      {
        "id": 1,
        "layer": "teeth",
        "name": "teeth",
        "rarity": "original"
      },
      {
        "id": 1,
        "layer": "pupils",
        "name": "pupils",
        "rarity": "original"
      },
      {
        "id": 1,
        "layer": "lips",
        "name": "lips",
        "rarity": "original"
      },
      {
        "id": 1,
        "layer": "blunt_body",
        "name": "blunt_body",
        "rarity": "original"
      },
      {
        "id": 1,
        "layer": "blunt_smoke",
        "name": "blunt_smoke",
        "rarity": "original"
      }
    ]
  },
  {
    "hash": "01112631415161718191101111122",
    "decodedHash": [
      {
        "0": 1
      },
      {
        "1": 1
      },
      {
        "2": 6
      },
      {
        "3": 1
      },
      {
        "4": 1
      },
      {
        "5": 1
      },
      {
        "6": 1
      },
      {
        "7": 1
      },
      {
        "8": 1
      },
      {
        "9": 1
      },
      {
        "10": 1
      },
      {
        "11": 1
      },
      {
        "12": 2
      }
    ],
    "edition": 5,
    "date": 1644552326205,
    "attributes": [
      {
        "id": 1,
        "layer": "nameplate",
        "name": "nameplate",
        "rarity": "original"
      },
      {
        "id": 1,
        "layer": "face",
        "name": "face",
        "rarity": "original"
      },
      {
        "id": 6,
        "layer": "hair",
        "name": "hair 7",
        "rarity": "original"
      },
      {
        "id": 1,
        "layer": "moustache",
        "name": "moustache",
        "rarity": "original"
      },
      {
        "id": 1,
        "layer": "eyebrows",
        "name": "eyebrows",
        "rarity": "original"
      },
      {
        "id": 1,
        "layer": "goatee",
        "name": "goatee",
        "rarity": "original"
      },
      {
        "id": 1,
        "layer": "nose",
        "name": "nose",
        "rarity": "original"
      },
      {
        "id": 1,
        "layer": "eyes",
        "name": "eyes",
        "rarity": "original"
      },
      {
        "id": 1,
        "layer": "teeth",
        "name": "teeth",
        "rarity": "original"
      },
      {
        "id": 1,
        "layer": "pupils",
        "name": "pupils",
        "rarity": "original"
      },
      {
        "id": 1,
        "layer": "lips",
        "name": "lips",
        "rarity": "original"
      },
      {
        "id": 1,
        "layer": "blunt_body",
        "name": "blunt_body",
        "rarity": "original"
      },
      {
        "id": 2,
        "layer": "blunt_smoke",
        "name": "blunt_smokeeddish",
        "rarity": "rare"
      }
    ]
  },
  {
    "hash": "01112131415161718191101111122",
    "decodedHash": [
      {
        "0": 1
      },
      {
        "1": 1
      },
      {
        "2": 1
      },
      {
        "3": 1
      },
      {
        "4": 1
      },
      {
        "5": 1
      },
      {
        "6": 1
      },
      {
        "7": 1
      },
      {
        "8": 1
      },
      {
        "9": 1
      },
      {
        "10": 1
      },
      {
        "11": 1
      },
      {
        "12": 2
      }
    ],
    "edition": 6,
    "date": 1644552327067,
    "attributes": [
      {
        "id": 1,
        "layer": "nameplate",
        "name": "nameplate",
        "rarity": "original"
      },
      {
        "id": 1,
        "layer": "face",
        "name": "face",
        "rarity": "original"
      },
      {
        "id": 1,
        "layer": "hair",
        "name": "hair 2",
        "rarity": "original"
      },
      {
        "id": 1,
        "layer": "moustache",
        "name": "moustache",
        "rarity": "original"
      },
      {
        "id": 1,
        "layer": "eyebrows",
        "name": "eyebrows",
        "rarity": "original"
      },
      {
        "id": 1,
        "layer": "goatee",
        "name": "goatee",
        "rarity": "original"
      },
      {
        "id": 1,
        "layer": "nose",
        "name": "nose",
        "rarity": "original"
      },
      {
        "id": 1,
        "layer": "eyes",
        "name": "eyes",
        "rarity": "original"
      },
      {
        "id": 1,
        "layer": "teeth",
        "name": "teeth",
        "rarity": "original"
      },
      {
        "id": 1,
        "layer": "pupils",
        "name": "pupils",
        "rarity": "original"
      },
      {
        "id": 1,
        "layer": "lips",
        "name": "lips",
        "rarity": "original"
      },
      {
        "id": 1,
        "layer": "blunt_body",
        "name": "blunt_body",
        "rarity": "original"
      },
      {
        "id": 2,
        "layer": "blunt_smoke",
        "name": "blunt_smokeeddish",
        "rarity": "rare"
      }
    ]
  },
  {
    "hash": "01112431415161718191101111121",
    "decodedHash": [
      {
        "0": 1
      },
      {
        "1": 1
      },
      {
        "2": 4
      },
      {
        "3": 1
      },
      {
        "4": 1
      },
      {
        "5": 1
      },
      {
        "6": 1
      },
      {
        "7": 1
      },
      {
        "8": 1
      },
      {
        "9": 1
      },
      {
        "10": 1
      },
      {
        "11": 1
      },
      {
        "12": 1
      }
    ],
    "edition": 7,
    "date": 1644552327933,
    "attributes": [
      {
        "id": 1,
        "layer": "nameplate",
        "name": "nameplate",
        "rarity": "original"
      },
      {
        "id": 1,
        "layer": "face",
        "name": "face",
        "rarity": "original"
      },
      {
        "id": 4,
        "layer": "hair",
        "name": "hair 5",
        "rarity": "original"
      },
      {
        "id": 1,
        "layer": "moustache",
        "name": "moustache",
        "rarity": "original"
      },
      {
        "id": 1,
        "layer": "eyebrows",
        "name": "eyebrows",
        "rarity": "original"
      },
      {
        "id": 1,
        "layer": "goatee",
        "name": "goatee",
        "rarity": "original"
      },
      {
        "id": 1,
        "layer": "nose",
        "name": "nose",
        "rarity": "original"
      },
      {
        "id": 1,
        "layer": "eyes",
        "name": "eyes",
        "rarity": "original"
      },
      {
        "id": 1,
        "layer": "teeth",
        "name": "teeth",
        "rarity": "original"
      },
      {
        "id": 1,
        "layer": "pupils",
        "name": "pupils",
        "rarity": "original"
      },
      {
        "id": 1,
        "layer": "lips",
        "name": "lips",
        "rarity": "original"
      },
      {
        "id": 1,
        "layer": "blunt_body",
        "name": "blunt_body",
        "rarity": "original"
      },
      {
        "id": 1,
        "layer": "blunt_smoke",
        "name": "blunt_smoke",
        "rarity": "original"
      }
    ]
  },
  {
    "hash": "01112131415161718191101111121",
    "decodedHash": [
      {
        "0": 1
      },
      {
        "1": 1
      },
      {
        "2": 1
      },
      {
        "3": 1
      },
      {
        "4": 1
      },
      {
        "5": 1
      },
      {
        "6": 1
      },
      {
        "7": 1
      },
      {
        "8": 1
      },
      {
        "9": 1
      },
      {
        "10": 1
      },
      {
        "11": 1
      },
      {
        "12": 1
      }
    ],
    "edition": 8,
    "date": 1644552328814,
    "attributes": [
      {
        "id": 1,
        "layer": "nameplate",
        "name": "nameplate",
        "rarity": "original"
      },
      {
        "id": 1,
        "layer": "face",
        "name": "face",
        "rarity": "original"
      },
      {
        "id": 1,
        "layer": "hair",
        "name": "hair 2",
        "rarity": "original"
      },
      {
        "id": 1,
        "layer": "moustache",
        "name": "moustache",
        "rarity": "original"
      },
      {
        "id": 1,
        "layer": "eyebrows",
        "name": "eyebrows",
        "rarity": "original"
      },
      {
        "id": 1,
        "layer": "goatee",
        "name": "goatee",
        "rarity": "original"
      },
      {
        "id": 1,
        "layer": "nose",
        "name": "nose",
        "rarity": "original"
      },
      {
        "id": 1,
        "layer": "eyes",
        "name": "eyes",
        "rarity": "original"
      },
      {
        "id": 1,
        "layer": "teeth",
        "name": "teeth",
        "rarity": "original"
      },
      {
        "id": 1,
        "layer": "pupils",
        "name": "pupils",
        "rarity": "original"
      },
      {
        "id": 1,
        "layer": "lips",
        "name": "lips",
        "rarity": "original"
      },
      {
        "id": 1,
        "layer": "blunt_body",
        "name": "blunt_body",
        "rarity": "original"
      },
      {
        "id": 1,
        "layer": "blunt_smoke",
        "name": "blunt_smoke",
        "rarity": "original"
      }
    ]
  },
  {
    "hash": "01112231415161718191101111121",
    "decodedHash": [
      {
        "0": 1
      },
      {
        "1": 1
      },
      {
        "2": 2
      },
      {
        "3": 1
      },
      {
        "4": 1
      },
      {
        "5": 1
      },
      {
        "6": 1
      },
      {
        "7": 1
      },
      {
        "8": 1
      },
      {
        "9": 1
      },
      {
        "10": 1
      },
      {
        "11": 1
      },
      {
        "12": 1
      }
    ],
    "edition": 9,
    "date": 1644552329699,
    "attributes": [
      {
        "id": 1,
        "layer": "nameplate",
        "name": "nameplate",
        "rarity": "original"
      },
      {
        "id": 1,
        "layer": "face",
        "name": "face",
        "rarity": "original"
      },
      {
        "id": 2,
        "layer": "hair",
        "name": "hair 3",
        "rarity": "original"
      },
      {
        "id": 1,
        "layer": "moustache",
        "name": "moustache",
        "rarity": "original"
      },
      {
        "id": 1,
        "layer": "eyebrows",
        "name": "eyebrows",
        "rarity": "original"
      },
      {
        "id": 1,
        "layer": "goatee",
        "name": "goatee",
        "rarity": "original"
      },
      {
        "id": 1,
        "layer": "nose",
        "name": "nose",
        "rarity": "original"
      },
      {
        "id": 1,
        "layer": "eyes",
        "name": "eyes",
        "rarity": "original"
      },
      {
        "id": 1,
        "layer": "teeth",
        "name": "teeth",
        "rarity": "original"
      },
      {
        "id": 1,
        "layer": "pupils",
        "name": "pupils",
        "rarity": "original"
      },
      {
        "id": 1,
        "layer": "lips",
        "name": "lips",
        "rarity": "original"
      },
      {
        "id": 1,
        "layer": "blunt_body",
        "name": "blunt_body",
        "rarity": "original"
      },
      {
        "id": 1,
        "layer": "blunt_smoke",
        "name": "blunt_smoke",
        "rarity": "original"
      }
    ]
  },
  {
    "hash": "01112231415161718191101111121",
    "decodedHash": [
      {
        "0": 1
      },
      {
        "1": 1
      },
      {
        "2": 2
      },
      {
        "3": 1
      },
      {
        "4": 1
      },
      {
        "5": 1
      },
      {
        "6": 1
      },
      {
        "7": 1
      },
      {
        "8": 1
      },
      {
        "9": 1
      },
      {
        "10": 1
      },
      {
        "11": 1
      },
      {
        "12": 1
      }
    ],
    "edition": 10,
    "date": 1644552330649,
    "attributes": [
      {
        "id": 1,
        "layer": "nameplate",
        "name": "nameplate",
        "rarity": "original"
      },
      {
        "id": 1,
        "layer": "face",
        "name": "face",
        "rarity": "original"
      },
      {
        "id": 2,
        "layer": "hair",
        "name": "hair 3",
        "rarity": "original"
      },
      {
        "id": 1,
        "layer": "moustache",
        "name": "moustache",
        "rarity": "original"
      },
      {
        "id": 1,
        "layer": "eyebrows",
        "name": "eyebrows",
        "rarity": "original"
      },
      {
        "id": 1,
        "layer": "goatee",
        "name": "goatee",
        "rarity": "original"
      },
      {
        "id": 1,
        "layer": "nose",
        "name": "nose",
        "rarity": "original"
      },
      {
        "id": 1,
        "layer": "eyes",
        "name": "eyes",
        "rarity": "original"
      },
      {
        "id": 1,
        "layer": "teeth",
        "name": "teeth",
        "rarity": "original"
      },
      {
        "id": 1,
        "layer": "pupils",
        "name": "pupils",
        "rarity": "original"
      },
      {
        "id": 1,
        "layer": "lips",
        "name": "lips",
        "rarity": "original"
      },
      {
        "id": 1,
        "layer": "blunt_body",
        "name": "blunt_body",
        "rarity": "original"
      },
      {
        "id": 1,
        "layer": "blunt_smoke",
        "name": "blunt_smoke",
        "rarity": "original"
      }
    ]
  }
]